agile_py/__init__.py
agile_py/cli/__init__.py
agile_py/cli/actions.py
agile_py/cli/cli.py
agile_py/cli/utils.py
agile_py/core/__init__.py
agile_py/core/utils.py
agile_py/settings/README.md
agile_py/settings/gitignore
agile_py/settings/pre-commit-config.yaml
agile_py/settings/pyproject.toml
agile_py/settings/setup.py
agile_py/settings/vscode_settings.json
agile_py/settings/ga/publish-to-pypi.yml
agile_py/settings/license/APACHE2
agile_py/settings/license/BSD3
agile_py/settings/license/GPL3
agile_py/settings/license/LGPL
agile_py/settings/license/MIT
agile_py-0.1.2.dist-info/LICENSE
agile_py-0.1.2.dist-info/METADATA
agile_py-0.1.2.dist-info/WHEEL
agile_py-0.1.2.dist-info/entry_points.txt
agile_py-0.1.2.dist-info/top_level.txt
agile_py-0.1.2.dist-info/RECORD
