Metadata-Version: 2.1
Name: agile-py
Version: 0.1.2
Summary: agile python project utilities
Home-page: https://github.com/Janus-Shiau/agile-py
Author: Jia-Yau Shiau
Author-email: jiayau.shiau@gmail.com
License: Apache Software License (Apache-2.0)
Requires-Python: >=3.7
License-File: LICENSE
Requires-Dist: click
Requires-Dist: rich
Requires-Dist: black
Requires-Dist: isort
Requires-Dist: ruamel.yaml
Requires-Dist: toml
Requires-Dist: open-serializer
